cookieless/__init__.py
cookieless/config.py
cookieless/cryptsession.py
cookieless/decorators.py
cookieless/example_settings.py
cookieless/middleware.py
cookieless/models.py
cookieless/templatetags/__init__.py
cookieless/templatetags/cookieless_tags.py
cookieless/tests/README.txt
cookieless/tests/__init__.py
cookieless/tests/base.py
cookieless/tests/functional_tests.py
cookieless/tests/settings.py
cookieless/tests/signal_functional_test.py
cookieless/tests/test_urls.py
cookieless/tests/unit_tests.py
cookieless/tests/urls.py
cookieless/tests/views.py
cookieless/tests/wsgi.py
cookieless/tests/templates/classview.html
django_cookieless-1.2.dist-info/METADATA
django_cookieless-1.2.dist-info/WHEEL
django_cookieless-1.2.dist-info/entry_points.txt
django_cookieless-1.2.dist-info/top_level.txt
django_cookieless-1.2.dist-info/RECORD
