Metadata-Version: 2.1
Name: django-cookieless
Version: 1.2
Summary: Django cookie free sessions optional decorator
Home-page: https://github.com/edcrewe/django-cookieless
Author: Ed Crewe
Author-email: edmundcrewe@gmail.com
License: Apache2
Keywords: Django,No cookies,cookieless
Platform: UNKNOWN
Classifier: Programming Language :: Python
Classifier: Topic :: Software Development :: Libraries :: Python Modules
Classifier: Development Status :: 4 - Beta
Classifier: Framework :: Django
Classifier: License :: OSI Approved :: Apache Software License
Requires-Dist: setuptools
Requires-Dist: cryptography
